main.py
installers/__init__.py
installers/ffmpeg/__init__.py
installers/ffmpeg/ffmpeg.sh
hogpi_install-0.1.3.dist-info/LICENSE
hogpi_install-0.1.3.dist-info/METADATA
hogpi_install-0.1.3.dist-info/WHEEL
hogpi_install-0.1.3.dist-info/entry_points.txt
hogpi_install-0.1.3.dist-info/top_level.txt
hogpi_install-0.1.3.dist-info/RECORD
