Metadata-Version: 2.1
Name: hogpi-install
Version: 0.1.3
Summary: The official tech4nature installer
Home-page: UNKNOWN
Author: Jack Whitehorn
Author-email: jackwh.whitehorn@gmail.com
License: UNKNOWN
Platform: UNKNOWN
Classifier: Programming Language :: Python :: 3
Classifier: License :: OSI Approved :: MIT License
Classifier: Operating System :: OS Independent
Requires-Python: >=3.6
Requires-Dist: click (==7.0)
Requires-Dist: PyInquirer (==1.0.3)
